{"id":"KCRJ7R33N2H7Z","name":"wallhaven-x1dqjz","size":3368581,"ext":"png","tags":[],"folders":["KCRJ7QUGJNLPQ"],"isDeleted":false,"url":"","annotation":"","modificationTime":1595069546685,"height":1357,"width":1919,"lastModified":1595069802752,"palettes":[{"color":[244,242,201],"ratio":35},{"color":[48,71,55],"ratio":19},{"color":[127,134,133],"ratio":13},{"color":[173,152,172],"ratio":8},{"color":[188,200,113],"ratio":8},{"color":[217,223,145],"ratio":7},{"color":[106,90,116],"ratio":2.58},{"color":[185,182,192],"ratio":2.58},{"color":[109,128,75],"ratio":2.27}]}