{"id":"KCRJ7R33NBOHL","name":"wallhaven-ym3kzd","size":4162610,"ext":"png","tags":[],"folders":["KCRJ7QUGJNLPQ"],"isDeleted":false,"url":"https://wallhaven.cc/w/","annotation":"","modificationTime":1595069541774,"height":1125,"width":2000,"lastModified":1595126495764,"palettes":[{"color":[30,38,44],"ratio":56},{"color":[68,79,93],"ratio":12},{"color":[106,113,130],"ratio":9},{"color":[201,176,179],"ratio":8},{"color":[76,57,56],"ratio":5},{"color":[114,83,81],"ratio":3.22},{"color":[114,151,184],"ratio":2.44},{"color":[81,101,105],"ratio":1.17},{"color":[193,91,68],"ratio":0.76},{"color":[129,151,155],"ratio":0.39}],"star":3}