{"id":"KCRJ7R3DXY223","name":"wallhaven-2ew9vx","size":1396155,"ext":"jpg","tags":[],"folders":["KCRJ7QUGJNLPQ"],"isDeleted":false,"url":"","annotation":"","modificationTime":1595069671441,"height":1440,"width":2560,"orientation":1,"lastModified":1595069859519,"palettes":[{"color":[118,160,176],"ratio":55},{"color":[216,209,211],"ratio":14},{"color":[91,100,49],"ratio":12},{"color":[175,186,192],"ratio":11},{"color":[143,161,105],"ratio":2.27},{"color":[91,113,134],"ratio":1.29},{"color":[192,94,68],"ratio":1.03},{"color":[148,176,74],"ratio":1},{"color":[62,92,101],"ratio":0.34}]}