{"id":"KCRJ7R3EQWEGH","name":"custom-b28161","size":510829,"ext":"jpg","tags":[],"folders":["KCRJ7QUHQ0UZD"],"isDeleted":false,"url":"","annotation":"","modificationTime":1595069717367,"height":2160,"width":3840,"orientation":1,"lastModified":1595069876916,"palettes":[{"color":[4,4,59],"ratio":81},{"color":[70,4,65],"ratio":6},{"color":[34,4,68],"ratio":3.44},{"color":[4,4,44],"ratio":2.81},{"color":[124,4,45],"ratio":2.66},{"color":[20,4,64],"ratio":1.29},{"color":[9,4,68],"ratio":0.78},{"color":[4,4,36],"ratio":0.37}]}