{"id":"KCRJ7R3CH1U8Y","name":"wallhaven-4o5pv9","size":176395,"ext":"jpg","tags":[],"folders":["KCRJ7QUGJNLPQ"],"isDeleted":false,"url":"","annotation":"","modificationTime":1595069661997,"height":1200,"width":1920,"lastModified":1595069855340,"palettes":[{"color":[251,249,247],"ratio":85},{"color":[78,73,87],"ratio":5},{"color":[187,152,157],"ratio":4.85},{"color":[246,195,177],"ratio":1.36},{"color":[215,79,89],"ratio":0.92},{"color":[114,125,148],"ratio":0.57},{"color":[151,73,84],"ratio":0.52},{"color":[197,173,102],"ratio":0.38}]}