{"id":"KCSF0P41L9GRW","name":"custom-771b01","size":445700,"ext":"jpg","tags":["壁纸推荐","原创人物","特写","梦夏 Shimmer"],"folders":["KCXCXPTNZFLJR"],"isDeleted":false,"url":"https://h.bilibili.com/11099590","annotation":"","modificationTime":1595122949665,"height":1578,"width":2805,"lastModified":1595487732617,"palettes":[{"color":[251,227,227],"ratio":84,"$$hashKey":"object:1387"},{"color":[230,182,179],"ratio":5,"$$hashKey":"object:1388"},{"color":[98,47,62],"ratio":3.71,"$$hashKey":"object:1389"},{"color":[214,156,154],"ratio":1.9,"$$hashKey":"object:1390"},{"color":[180,142,152],"ratio":1.2,"$$hashKey":"object:1391"},{"color":[159,99,111],"ratio":1.03,"$$hashKey":"object:1392"},{"color":[239,196,187],"ratio":0.98,"$$hashKey":"object:1393"},{"color":[229,172,163],"ratio":0.73,"$$hashKey":"object:1394"},{"color":[210,199,202],"ratio":0.39,"$$hashKey":"object:1395"}],"orientation":1}