{"id":"KCRJ7R3CBXSZM","name":"wallhaven-4dp71l","size":383088,"ext":"png","tags":["壁纸推荐","物语系列","贝木泥舟","特写"],"folders":["KCRJ7QUGJNLPQ"],"isDeleted":false,"url":"https://wallhaven.cc/w/4dp71l","annotation":"","modificationTime":1595069664802,"height":1080,"width":1920,"lastModified":1595126959939,"palettes":[{"color":[18,18,18],"ratio":47,"$$hashKey":"object:21800"},{"color":[208,208,208],"ratio":15,"$$hashKey":"object:21801"},{"color":[116,116,116],"ratio":9,"$$hashKey":"object:21802"},{"color":[67,67,67],"ratio":9,"$$hashKey":"object:21803"},{"color":[52,52,52],"ratio":4.27,"$$hashKey":"object:21804"},{"color":[84,84,84],"ratio":2.66,"$$hashKey":"object:21805"},{"color":[148,148,148],"ratio":2.2,"$$hashKey":"object:21806"},{"color":[92,92,92],"ratio":2.2,"$$hashKey":"object:21807"},{"color":[164,164,164],"ratio":2.08,"$$hashKey":"object:21808"},{"color":[140,140,140],"ratio":1.81,"$$hashKey":"object:21809"},{"color":[156,156,156],"ratio":1.61,"$$hashKey":"object:21810"}],"star":3}