{"id":"KCRJ7R39L5BGL","name":"wallhaven-96w8e8","size":2073805,"ext":"png","tags":[],"folders":["KCRJ7QUGJNLPQ"],"isDeleted":false,"url":"https://wallhaven.cc/w/","annotation":"","modificationTime":1595069627263,"height":1440,"width":2560,"lastModified":1595126495226,"palettes":[{"color":[22,27,69],"ratio":60},{"color":[103,71,99],"ratio":9},{"color":[213,137,150],"ratio":8},{"color":[22,54,106],"ratio":8},{"color":[39,76,132],"ratio":4.1},{"color":[57,97,151],"ratio":3.25},{"color":[225,80,76],"ratio":1.98},{"color":[75,126,178],"ratio":1.54},{"color":[245,221,229],"ratio":0.98},{"color":[166,53,64],"ratio":0.95}],"star":3}