{"id":"KCRVBJH5XYH32","name":"wallhaven-j5gjky","size":689075,"ext":"jpg","tags":["壁纸推荐","我的青春恋爱物语果然有问题","由比滨结衣","雪之下雪乃"],"folders":["KCRJ7QUGJNLPQ"],"isDeleted":false,"url":"https://wallhaven.cc/w/j5gjky","annotation":"","modificationTime":1595089863257,"height":1440,"width":2560,"palettes":[{"color":[251,243,242],"ratio":80,"$$hashKey":"object:2411"},{"color":[67,62,69],"ratio":13,"$$hashKey":"object:2412"},{"color":[201,154,147],"ratio":2.88,"$$hashKey":"object:2413"},{"color":[225,196,191],"ratio":1.27,"$$hashKey":"object:2414"},{"color":[128,93,93],"ratio":0.51,"$$hashKey":"object:2415"},{"color":[177,106,102],"ratio":0.39,"$$hashKey":"object:2416"}],"lastModified":1595560277659}