{"id":"KCS4T1604OUP0","name":"custom-12961f","size":881469,"ext":"jpg","tags":["壁纸推荐","原创人物","特写","梦夏 Shimmer"],"folders":["KCXCXPTNZFLJR"],"isDeleted":false,"url":"https://h.bilibili.com/3929698","annotation":"","modificationTime":1595105795880,"noThumbnail":true,"width":2492,"height":1402,"lastModified":1595421827482,"palettes":[{"color":[175,162,155],"ratio":68,"$$hashKey":"object:7988"},{"color":[222,206,198],"ratio":12,"$$hashKey":"object:7989"},{"color":[37,18,27],"ratio":11,"$$hashKey":"object:7990"},{"color":[231,221,216],"ratio":4.18,"$$hashKey":"object:7991"},{"color":[127,47,52],"ratio":2.52,"$$hashKey":"object:7992"},{"color":[156,99,108],"ratio":1,"$$hashKey":"object:7993"},{"color":[142,130,116],"ratio":0.34,"$$hashKey":"object:7994"}]}