{"id":"KCRJ7R3DLX4WQ","name":"wallhaven-2ee95g","size":6525573,"ext":"png","tags":["未知出处","未知人物","动画风景","壁纸推荐"],"folders":["KCRJ7QUGJNLPQ"],"isDeleted":false,"url":"https://wallhaven.cc/w/2ee95g","annotation":"","modificationTime":1595069672614,"height":1440,"width":2560,"lastModified":1595122800183,"palettes":[{"color":[73,122,178],"ratio":48,"$$hashKey":"object:13595"},{"color":[24,25,55],"ratio":19,"$$hashKey":"object:13596"},{"color":[195,134,144],"ratio":15,"$$hashKey":"object:13597"},{"color":[144,114,146],"ratio":14,"$$hashKey":"object:13598"},{"color":[88,78,106],"ratio":1.76,"$$hashKey":"object:13599"},{"color":[49,50,92],"ratio":0.54,"$$hashKey":"object:13600"}],"star":3}