{"id":"KCRJ7R380R6Q5","name":"wallhaven-g86oj3","size":7835269,"ext":"jpg","tags":[],"folders":["KCRJ7QUGJNLPQ"],"isDeleted":false,"url":"","annotation":"","modificationTime":1595069601852,"height":6000,"width":4000,"orientation":1,"lastModified":1595069828392,"palettes":[{"color":[167,13,14],"ratio":39},{"color":[37,30,30],"ratio":28},{"color":[219,191,192],"ratio":11},{"color":[89,44,45],"ratio":9},{"color":[228,39,40],"ratio":4.73},{"color":[150,105,107],"ratio":3.97},{"color":[164,131,140],"ratio":1.28}]}