{"id":"KCRJ7R32ZW20B","name":"wallhaven-zmrmdo","size":891267,"ext":"png","tags":[],"folders":["KCRJ7QUGJNLPQ"],"isDeleted":false,"url":"https://wallhaven.cc/w/","annotation":"","modificationTime":1595069533720,"height":1600,"width":2560,"lastModified":1595126495806,"palettes":[{"color":[20,22,24],"ratio":38},{"color":[82,71,71],"ratio":20},{"color":[225,65,83],"ratio":13},{"color":[134,66,73],"ratio":11},{"color":[53,41,42],"ratio":9},{"color":[59,59,60],"ratio":5},{"color":[67,68,68],"ratio":0.49},{"color":[89,85,86],"ratio":0.43}],"star":3}