{"id":"KCRJ7R3BCICCN","name":"wallhaven-39yr8y","size":7229231,"ext":"png","tags":[],"folders":["KCRJ7QUGJNLPQ"],"isDeleted":false,"url":"https://wallhaven.cc/w/","annotation":"","modificationTime":1595069641472,"height":2160,"width":4276,"lastModified":1595126495165,"palettes":[{"color":[17,23,30],"ratio":42},{"color":[29,68,91],"ratio":15},{"color":[48,90,108],"ratio":11},{"color":[67,110,128],"ratio":9},{"color":[163,114,106],"ratio":5},{"color":[100,128,134],"ratio":5},{"color":[99,94,96],"ratio":4.82},{"color":[60,56,60],"ratio":3.22},{"color":[38,55,65],"ratio":1.89}],"star":3}